dpp_runner/VERSION
dpp_runner/__init__.py
dpp_runner/lib.py
dpp_runner/server.py
os_dpp_runner-0.1.0.dist-info/LICENSE.md
os_dpp_runner-0.1.0.dist-info/METADATA
os_dpp_runner-0.1.0.dist-info/WHEEL
os_dpp_runner-0.1.0.dist-info/top_level.txt
os_dpp_runner-0.1.0.dist-info/RECORD
